covjsonkit/Coverage.py
covjsonkit/CoverageCollection.py
covjsonkit/__init__.py
covjsonkit/api.py
covjsonkit/config.py
covjsonkit/param_db.py
covjsonkit/utils.py
covjsonkit/version.py
covjsonkit/data/__init__.py
covjsonkit/data/dwd/param.json
covjsonkit/data/dwd/param_id.json
covjsonkit/data/dwd/unit.json
covjsonkit/data/ecmwf/param.json
covjsonkit/data/ecmwf/param_id.json
covjsonkit/data/ecmwf/unit.json
covjsonkit/decoder/BoundingBox.py
covjsonkit/decoder/Circle.py
covjsonkit/decoder/Frame.py
covjsonkit/decoder/Grid.py
covjsonkit/decoder/Path.py
covjsonkit/decoder/Position.py
covjsonkit/decoder/Shapefile.py
covjsonkit/decoder/TimeSeries.py
covjsonkit/decoder/VerticalProfile.py
covjsonkit/decoder/Wkt.py
covjsonkit/decoder/__init__.py
covjsonkit/decoder/decoder.py
covjsonkit/encoder/BoundingBox.py
covjsonkit/encoder/Circle.py
covjsonkit/encoder/Frame.py
covjsonkit/encoder/Grid.py
covjsonkit/encoder/Path.py
covjsonkit/encoder/Position.py
covjsonkit/encoder/Shapefile.py
covjsonkit/encoder/TimeSeries.py
covjsonkit/encoder/VerticalProfile.py
covjsonkit/encoder/Wkt.py
covjsonkit/encoder/__init__.py
covjsonkit/encoder/encoder.py
covjsonkit-0.2.10.dist-info/LICENSE
covjsonkit-0.2.10.dist-info/METADATA
covjsonkit-0.2.10.dist-info/WHEEL
covjsonkit-0.2.10.dist-info/top_level.txt
covjsonkit-0.2.10.dist-info/RECORD
