Metadata-Version: 2.1
Name: covjsonkit
Version: 0.2.10
Home-page: https://github.com/ecmwf/covjsonkit
Author: ECMWF
Author-email: James.Hawkes@ecmwf.int, Adam.Warde@ecmwf.int, Mathilde.Leuridan@ecmwf.int
License-File: LICENSE
Requires-Dist: pandas <3
Requires-Dist: orjson
Requires-Dist: xarray
Requires-Dist: covjson-pydantic
Requires-Dist: conflator
Requires-Dist: scipy
Provides-Extra: geo
Requires-Dist: rasterio ; extra == 'geo'
Requires-Dist: shapely ; extra == 'geo'
